yahooooo/__init__.py
yahooooo/birds.py
yahooooo/mammals.py
yahooooo/test.py
yahooooo-0.1.dist-info/LICENSE.txt
yahooooo-0.1.dist-info/METADATA
yahooooo-0.1.dist-info/WHEEL
yahooooo-0.1.dist-info/top_level.txt
yahooooo-0.1.dist-info/RECORD
